mtxp/__init__.py
mtxp/app.py
mtxp/config.py
mtxp/contentful.py
mtxp/settings.py
mtxp/setup.py
mtxp/cli/__init__.py
mtxp/cli/cli.py
mtxp/data/mtxtun.bundle.js
mtxp/data/mtxtun.yml
mtxp/data/sshd.sh
mtxp/data/tun.js
mtxp/data/v2ray.config.json
mtxp/mtxp/__init__.py
mtxp/mtxp/views.py
mtxp/services/__init__.py
mtxp/services/clash.py
mtxp/services/mtxtun.py
mtxp/services/nginx.py
mtxp/services/openvpn.py
mtxp/services/pf.py
mtxp/services/pf_agent.py
mtxp/services/phpfpm.py
mtxp/services/services.py
mtxp/services/tailscale.py
mtxp/services/tor.py
mtxp/services/wordpress.py
mtxp/setup/__init__.py
mtxp-0.0.212.dist-info/METADATA
mtxp-0.0.212.dist-info/WHEEL
mtxp-0.0.212.dist-info/entry_points.txt
mtxp-0.0.212.dist-info/top_level.txt
mtxp-0.0.212.dist-info/zip-safe
mtxp-0.0.212.dist-info/RECORD
