Metadata-Version: 2.1
Name: mtxp
Version: 0.0.212
Summary: The funniest joke in the world
Home-page: http://github.com/storborg/funniest
Author: Flying Circus
Author-email: flyingcircus@example.com
License: MIT
Keywords: funniest joke comedy flying circus
Classifier: Programming Language :: Python :: 3
Classifier: Programming Language :: Python :: 3.6
Requires-Dist: requests
Requires-Dist: python-dotenv
Requires-Dist: flask
Requires-Dist: mtlibs
Requires-Dist: pyyaml
Requires-Dist: docker
Requires-Dist: markupsafe
Requires-Dist: contentful
Requires-Dist: contentful-management
Requires-Dist: paramiko
